py_common/__init__.py
py_common/logger.py
py_common/logger/__init__.py
py_common/logger/logger.py
py_common/message_queue/__init__.py
py_common/message_queue/controller.py
py_common_network_task-1.3.4.dist-info/METADATA
py_common_network_task-1.3.4.dist-info/WHEEL
py_common_network_task-1.3.4.dist-info/top_level.txt
py_common_network_task-1.3.4.dist-info/RECORD
