Metadata-Version: 2.1
Name: py-common-network-task
Version: 1.3.4
Summary: Network Task packages
Author: Mor Dvash
Author-email: mordvash1@gmail.com
Requires-Python: >=3.8
Requires-Dist: kafka-python (==2.0.2)
